jam/__init__.py
jam/tests/__init__.py
jam/tests/test_annotation_mapping.py
jam/tests/test_highlight.py
jam/tests/test_many.py
jam/tests/test_nested.py
jam/tests/test_optional.py
marshmallow_jam-1.2.0.dist-info/METADATA
marshmallow_jam-1.2.0.dist-info/WHEEL
marshmallow_jam-1.2.0.dist-info/top_level.txt
marshmallow_jam-1.2.0.dist-info/RECORD
