Metadata-Version: 2.1
Name: marshmallow-jam
Version: 1.2.0
Summary: Some extra sweets for marshmallow.
Home-page: https://github.com/nonamenix/marshmallow-jam
Author: nonamenix
Author-email: nonamenix@gmail.com
License: UNKNOWN
Platform: UNKNOWN
Requires-Dist: marshmallow (>=3.0.0rc6)
